tamcolors/__init__.py
tamcolors/examples/__init__.py
tamcolors/examples/alpha.py
tamcolors/examples/basic.py
tamcolors/examples/clouds.py
tamcolors/examples/colors.py
tamcolors/examples/connection_loopback.py
tamcolors/examples/connection_multi_player.py
tamcolors/examples/host_loopback.py
tamcolors/examples/host_multi_player.py
tamcolors/examples/icon.py
tamcolors/examples/rgb_color.py
tamcolors/examples/sandy_check.py
tamcolors/examples/tabletennis.py
tamcolors/examples/tam_key_manager.py
tamcolors/examples/tam_keys.py
tamcolors/examples/tam_list_surface.py
tamcolors/examples/tam_loop.py
tamcolors/examples/tam_print.py
tamcolors/examples/tam_text_box.py
tamcolors/tam/__init__.py
tamcolors/tam/tam_loop.py
tamcolors/tam/tam_loop_io_handler.py
tamcolors/tam/tam_loop_io_tcp_handler.py
tamcolors/tam/tam_loop_receiver.py
tamcolors/tam/tam_loop_tcp_receiver.py
tamcolors/tam_basic/__init__.py
tamcolors/tam_basic/basic.py
tamcolors/tam_c/__init__.py
tamcolors/tam_c/_win_tam.cp38-win32.pyd
tamcolors/tam_c/_uni_tam_c/_uni_tam.cpp
tamcolors/tam_c/_uni_tam_c/uni_tam.cpp
tamcolors/tam_c/_uni_tam_c/uni_tam.h
tamcolors/tam_c/_win_tam_c/_win_tam.cpp
tamcolors/tam_c/_win_tam_c/win_tam.cpp
tamcolors/tam_c/_win_tam_c/win_tam.h
tamcolors/tam_c/_win_tam_c/vs140_dlls/arm/msvcp140.dll
tamcolors/tam_c/_win_tam_c/vs140_dlls/x64/msvcp140.dll
tamcolors/tam_c/_win_tam_c/vs140_dlls/x86/msvcp140.dll
tamcolors/tam_io/__init__.py
tamcolors/tam_io/ansi_256_drivers.py
tamcolors/tam_io/ansi_true_color_drivers.py
tamcolors/tam_io/any_drivers.py
tamcolors/tam_io/io_tam.py
tamcolors/tam_io/lin_drivers.py
tamcolors/tam_io/mac_drivers.py
tamcolors/tam_io/null_drivers.py
tamcolors/tam_io/tam_colors.py
tamcolors/tam_io/tam_drivers.py
tamcolors/tam_io/tam_identifier.py
tamcolors/tam_io/tam_keys.py
tamcolors/tam_io/tam_surface.py
tamcolors/tam_io/tcp_io.py
tamcolors/tam_io/uni_drivers.py
tamcolors/tam_io/win_drivers.py
tamcolors/tam_tools/__init__.py
tamcolors/tam_tools/tam_color_palette.py
tamcolors-1.3.0.dist-info/LICENSE
tamcolors-1.3.0.dist-info/METADATA
tamcolors-1.3.0.dist-info/WHEEL
tamcolors-1.3.0.dist-info/top_level.txt
tamcolors-1.3.0.dist-info/RECORD
