Metadata-Version: 2.1
Name: tamcolors
Version: 1.3.0
Summary: tamcolors standardizes console color output across multiple platforms
Home-page: https://github.com/cmcmarrow/tamcolors
Author: Charles McMarrow
Author-email: Charles.M.McMarrow@gmail.com
License: Apache Software License 2.0
Platform: UNKNOWN
Classifier: Development Status :: 5 - Production/Stable
Classifier: Environment :: Console
Classifier: Intended Audience :: Developers
Classifier: Natural Language :: English
Classifier: Operating System :: Microsoft :: Windows
Classifier: Operating System :: POSIX :: Linux
Classifier: Operating System :: MacOS :: MacOS X
Classifier: Programming Language :: C
Classifier: Programming Language :: C++
Classifier: Programming Language :: Python :: 3.6
Classifier: Programming Language :: Python :: 3.7
Classifier: Programming Language :: Python :: 3.8
Classifier: Programming Language :: Python :: 3.9
Classifier: Topic :: Terminals
Classifier: Topic :: Utilities
Provides-Extra: dev
Provides-Extra: encryption
